pyfcst/__init__.py
pyfcst/ips/__init__.py
pyfcst/ips/analysis/__init__.py
pyfcst/ips/analysis/distanceSD.py
pyfcst/ips/inout/__init__.py
pyfcst/ips/inout/input.py
pyfcst/ips/inout/output.py
pyfcst/ips/inout/printlog.py
pyfcst/util/__init__.py
pyfcst/util/baseclass.py
pyfcst-0.0.17.dist-info/LICENSE.txt
pyfcst-0.0.17.dist-info/METADATA
pyfcst-0.0.17.dist-info/WHEEL
pyfcst-0.0.17.dist-info/RECORD
